dynamic_pricing_ancil/__init__.py
dynamic_pricing_ancil/dyn-pric-classes/CustomLossFunctionDynPricJointModel.py
dynamic_pricing_ancil/dyn-pric-classes/DynamicPricingIndividualModels.py
dynamic_pricing_ancil/dyn-pric-classes/DynamicPricingOfPrimaryAndAncillaryProduct.py
dynamic_pricing_ancil/dyn-pric-classes/MABextendedLinUCBClassifier.py
dynamic_pricing_ancil/dyn-pric-classes/MultipleAncillaryProductsLinearDemand.py
dynamic_pricing_ancil/dyn-pric-classes/MultipleAncillaryProductsNonlinearDemand.py
dynamic_pricing_ancil/dyn-pric-functions/dp_ind_models_print_plot.py
dynamic_pricing_ancil/dyn-pric-functions/wtp_and_pax_arrival_distributions.py
dynamic_pricing_ancil/dyn-pric-metrics/dp_offline_metrics.py
dynamic_pricing_ancil/dyn-pric-metrics/dp_uplift.py
dynamic_pricing_ancil-0.0.1.dist-info/LICENSE
dynamic_pricing_ancil-0.0.1.dist-info/METADATA
dynamic_pricing_ancil-0.0.1.dist-info/WHEEL
dynamic_pricing_ancil-0.0.1.dist-info/top_level.txt
dynamic_pricing_ancil-0.0.1.dist-info/RECORD
