Metadata-Version: 2.1
Name: dynamic_pricing_ancil
Version: 0.0.1
Summary: A package containing various methods that can be used for dynamic pricing of airline ancillaries
Author-email: Petr Kocandrle <petr.kocandrle@amadeus.com>
Project-URL: Homepage, https://github.com/pypa/sampleproject
Project-URL: Issues, https://github.com/pypa/sampleproject/issues
Classifier: Programming Language :: Python :: 3
Classifier: License :: OSI Approved :: MIT License
Classifier: Operating System :: OS Independent
Requires-Python: >=3.8
License-File: LICENSE
